progressive_automations_python/__init__.py
progressive_automations_python/cli.py
progressive_automations_python/config.py
progressive_automations_python/deployment.py
progressive_automations_python/desk_controller.py
progressive_automations_python/duty_cycle.py
progressive_automations_python/movement_control.py
progressive_automations_python/prefect_flows.py
progressive_automations_python/skeleton.py
progressive_automations_python-0.1.4.dist-info/licenses/LICENSE.txt
progressive_automations_python-0.1.4.dist-info/METADATA
progressive_automations_python-0.1.4.dist-info/WHEEL
progressive_automations_python-0.1.4.dist-info/entry_points.txt
progressive_automations_python-0.1.4.dist-info/top_level.txt
progressive_automations_python-0.1.4.dist-info/RECORD
