Metadata-Version: 2.4
Name: progressive-automations-python
Version: 0.1.4
Summary: Python package for programmatically controlling progressive automations tools (e.g., LG-07 modular lifting column via FLTCON).
Home-page: https://progressive-automations-python.readthedocs.io/
Author: Sterling G. Baird
Author-email: sterling.baird@utoronto.ca
License: MIT
Project-URL: Documentation, https://pyscaffold.org/
Platform: any
Classifier: Development Status :: 4 - Beta
Classifier: Programming Language :: Python
License-File: LICENSE.txt
Requires-Dist: importlib-metadata; python_version < "3.8"
Requires-Dist: prefect>=3.0.0
Requires-Dist: rpi-lgpio; platform_machine == "aarch64" or platform_machine == "armv7l"
Provides-Extra: testing
Requires-Dist: setuptools; extra == "testing"
Requires-Dist: pytest; extra == "testing"
Requires-Dist: pytest-cov; extra == "testing"
Dynamic: license-file
